README.rst
pyhtml.py
setup.cfg
setup.py
PyHTML.egg-info/PKG-INFO
PyHTML.egg-info/SOURCES.txt
PyHTML.egg-info/dependency_links.txt
PyHTML.egg-info/not-zip-safe
PyHTML.egg-info/pbr.json
PyHTML.egg-info/requires.txt
PyHTML.egg-info/top_level.txt