Metadata-Version: 1.1
Name: PyHTML
Version: 0.6.0
Summary: Simple HTML generator for Python
Home-page: https://github.com/cenkalti/pyhtml
Author: Cenk Altı
Author-email: cenkalti@gmail.com
License: UNKNOWN
Keywords: html template markup
Platform: UNKNOWN
Classifier: Development Status :: 4 - Beta
Classifier: Intended Audience :: Developers
Classifier: License :: OSI Approved :: Apache Software License
Classifier: Operating System :: OS Independent
Classifier: Programming Language :: Python
Classifier: Programming Language :: Python :: 2.7
Classifier: Topic :: Internet :: WWW/HTTP :: Dynamic Content
Classifier: Topic :: Software Development :: Libraries :: Python Modules
